gym_minecraft_pygame/__init__.py
gym_minecraft_pygame/__main__.py
gym_minecraft_pygame/__version__.py
gym_minecraft_pygame/minecraft_env.py
gym_minecraft_pygame/utils.py
gym_minecraft_pygame/wrappers/__init__.py
gym_minecraft_pygame/wrappers/dict_space.py
tests/__init__.py
tests/test_dummy.py
gym_minecraft_pygame-0.1.0.dist-info/LICENSE
gym_minecraft_pygame-0.1.0.dist-info/METADATA
gym_minecraft_pygame-0.1.0.dist-info/WHEEL
gym_minecraft_pygame-0.1.0.dist-info/top_level.txt
gym_minecraft_pygame-0.1.0.dist-info/RECORD
