Metadata-Version: 2.1
Name: gym-minecraft-pygame
Version: 0.1.0
Summary: Gym Minecraft environment using Pygame
Home-page: https://github.com/whitemech/gym-minecraft-pygame.git
Author: Marco Favorito, Luca Iocchi
License: Apache License 2.0
Keywords: environment,agent,rl,openaigym,openai-gym,gym,minecraft
Platform: UNKNOWN
Classifier: Development Status :: 2 - Pre-Alpha
Classifier: Intended Audience :: Developers
Classifier: Natural Language :: English
Classifier: License :: OSI Approved :: Apache Software License
Classifier: Programming Language :: Python :: 3.6
Classifier: Programming Language :: Python :: 3.7
Requires-Python: >=3.6
Requires-Dist: gym
Requires-Dist: pygame
Requires-Dist: numpy
